kiloa/__init__.py
kiloa/kiloa.py
kiloa-1.0.3.dist-info/METADATA
kiloa-1.0.3.dist-info/WHEEL
kiloa-1.0.3.dist-info/top_level.txt
kiloa-1.0.3.dist-info/RECORD
