Metadata-Version: 2.4
Name: kiloa
Version: 1.0.3
Summary: مكتبة بايثون بتطوير مصطفى @D_B_HH
Home-page: https://github.com/D_B_HH/kiloa ; افتراضي، يمكن تغييره لاحقًا
Author: مصطفى
Author-email: em@ex@ex.com
License: MIT ; افتراضي، يمكن تغييره لاحقًا
Keywords: python,library,kiloa
Requires-Python: >=3.6
